<?xml version="1.0" encoding="utf-8"?>
<Solution xmlns="http://schemas.microsoft.com/sharepoint/" SolutionId="9695b8a5-c40a-41e6-bce1-e90938a81135" SharePointProductVersion="14.0">
  <Assemblies>
    <Assembly Location="SPSM.Common.dll" DeploymentTarget="GlobalAssemblyCache" />
    <Assembly Location="AWSSDK.dll" DeploymentTarget="GlobalAssemblyCache" />
    <Assembly Location="Microsoft.Practices.ServiceLocation.dll" DeploymentTarget="GlobalAssemblyCache" />
    <Assembly Location="Microsoft.Practices.SharePoint.Common.dll" DeploymentTarget="GlobalAssemblyCache" />
    <Assembly Location="Microsoft.WindowsAPICodePack.dll" DeploymentTarget="GlobalAssemblyCache" />
    <Assembly Location="Microsoft.WindowsAPICodePack.Shell.dll" DeploymentTarget="GlobalAssemblyCache" />
    <Assembly Location="SPSM.dll" DeploymentTarget="GlobalAssemblyCache" />
  </Assemblies>
  <TemplateFiles>
    <TemplateFile Location="Layouts\SPSM\Upload.aspx" />
  </TemplateFiles>
  <FeatureManifests>
    <FeatureManifest Location="SPStorageManager_Configuration\Feature.xml" />
    <FeatureManifest Location="SPStorageManager_Media\Feature.xml" />
  </FeatureManifests>
</Solution>